annextimelog/__init__.py
annextimelog/__main__.py
annextimelog/datetime.py
annextimelog/log.py
annextimelog/repo.py
annextimelog/run.py
annextimelog/test.py
annextimelog/token.py
annextimelog/utils.py
annextimelog-0.15.0.dist-info/LICENSES/GPL-3.0-or-later.txt
annextimelog-0.15.0.dist-info/METADATA
annextimelog-0.15.0.dist-info/WHEEL
annextimelog-0.15.0.dist-info/entry_points.txt
annextimelog-0.15.0.dist-info/RECORD
