Metadata-Version: 2.3
Name: annextimelog
Version: 0.15.0
Summary: Track time spent on projects, backed by Git Annex
Author: Yann Büchau
Author-email: nobodyinperson@posteo.de
Requires-Python: >=3.10,<4.0
Classifier: Development Status :: 3 - Alpha
Classifier: License :: OSI Approved :: GNU General Public License v3 (GPLv3)
Classifier: Programming Language :: Python :: 3
Classifier: Programming Language :: Python :: 3.10
Classifier: Programming Language :: Python :: 3.11
Classifier: Programming Language :: Python :: 3.12
Classifier: Programming Language :: Python :: 3.13
Classifier: Topic :: Software Development :: Version Control :: Git
Requires-Dist: rich (>=13.7.0,<14.0.0)
Requires-Dist: tzdata
Project-URL: Author on Mastodon, https://fosstodon.org/@nobodyinperson
Project-URL: Changelog, https://gitlab.com/nobodyinperson/annextimelog/-/blob/main/CHANGELOG.md?ref_type=heads
Project-URL: Homepage, https://gitlab.com/nobodyinperson/annextimelog
Project-URL: Repository, https://gitlab.com/nobodyinperson/annextimelog
